numworks_viewer/__init__.py
numworks_viewer/image_encoder.py
numworks_viewer/viewer.py
numworks_jpeg_viewer-0.0.3.dist-info/METADATA
numworks_jpeg_viewer-0.0.3.dist-info/WHEEL
numworks_jpeg_viewer-0.0.3.dist-info/licenses/LICENSE
numworks_jpeg_viewer-0.0.3.dist-info/RECORD
